<?xml version="1.0" encoding="utf-8"?>
<Defs>

  <ConceptDef ParentName="NotedOpportunisticBase">
    <defName>EditingMemes</defName>
    <label>editing memes</label>
    <helpText>You can edit memes by clicking on them.</helpText>
    <priority>10</priority>
    <gameMode>Entry</gameMode>
    <highlightTags>
      <li>MemeBox</li>
    </highlightTags>
  </ConceptDef>

  <ConceptDef ParentName="NotedOpportunisticBase">
    <defName>EditingPrecepts</defName>
    <label>editing precepts</label>
    <helpText>You can edit precepts by clicking on them.</helpText>
    <priority>1</priority>
    <gameMode>Entry</gameMode>
    <highlightTags>
      <li>PreceptBox</li>
    </highlightTags>
  </ConceptDef>

  <InstructionDef>
    <defName>ChooseIdeo</defName>
    <text>This page is for choosing the ideoligion of your colonists. The term ideoligion includes religions, ideologies, and every other belief system that defines a moral structure in the universe.\n\nThe PLAY CLASSIC option here will work - go ahead and click it!</text>
    <eventTagInitiate>PageStart-ChooseIdeo</eventTagInitiate>
    <actionTagsAllowed>
      <li>GotoPrevPage</li>
      <li>ButtonClassicIdeo</li>
    </actionTagsAllowed>
    <highlightTags>
      <li>ButtonClassicIdeo</li>
    </highlightTags>
    <rejectInputMessage>Please click PLAY CLASSIC to continue the tutorial.</rejectInputMessage>
  </InstructionDef>
  
</Defs>